jsdk/__init__.py
jsdk/exceptions.py
jsdk/manager.py
jsdk/models.py
jsdk-0.0.18.dist-info/LICENSE
jsdk-0.0.18.dist-info/METADATA
jsdk-0.0.18.dist-info/WHEEL
jsdk-0.0.18.dist-info/top_level.txt
jsdk-0.0.18.dist-info/RECORD
