Metadata-Version: 2.1
Name: jsdk
Version: 0.0.18
Summary: A package for interacting programmatically with Jasmin Gateway CLI
Home-page: https://github.com/Arolitec/jsdk
Author: Arolitec
Author-email: manouman@live.fr
License: MIT License
Project-URL: Bug Tracker, https://github.com/Arolitec/jsdk/issues
Keywords: jasmin,gateway,sms
Classifier: Programming Language :: Python :: 3
Classifier: License :: OSI Approved :: MIT License
Classifier: Operating System :: OS Independent
Requires-Python: >=3.6
License-File: LICENSE
Requires-Dist: pexpect
